subt/__init__.py
subt/main.py
subt/py.typed
subt-0.1.0.dist-info/METADATA
subt-0.1.0.dist-info/WHEEL
subt-0.1.0.dist-info/entry_points.txt
subt-0.1.0.dist-info/licenses/LICENSE
subt-0.1.0.dist-info/RECORD
