Metadata-Version: 2.4
Name: subt
Version: 0.1.0
Summary: Translate a subtitle file
Project-URL: Repository, https://github.com/eggplants/subt
Author-email: eggplants <w10776e8w@yahoo.co.jp>
License: MIT
License-File: LICENSE
Keywords: subtitle,translate
Classifier: Development Status :: 4 - Beta
Classifier: Environment :: Console
Classifier: Operating System :: OS Independent
Classifier: Programming Language :: Python :: 3 :: Only
Classifier: Programming Language :: Python :: 3.12
Classifier: Programming Language :: Python :: 3.13
Classifier: Programming Language :: Python :: 3.14
Classifier: Typing :: Typed
Requires-Python: <4,>=3.12
Requires-Dist: pysubs2<2,>=1.8
Requires-Dist: translatepy<3,>=2.3
